logdelta/__init__.py
logdelta/config_runner.py
logdelta/data_specific_preprocessing.py
logdelta/log_analysis_functions.py
logdelta/regex_masking.py
logdelta/subset_data_to_new_dir.py
logdelta-1.0.0.post1.dist-info/METADATA
logdelta-1.0.0.post1.dist-info/WHEEL
logdelta-1.0.0.post1.dist-info/entry_points.txt
logdelta-1.0.0.post1.dist-info/top_level.txt
logdelta-1.0.0.post1.dist-info/RECORD
