Metadata-Version: 2.1
Name: logdelta
Version: 1.0.0.post1
Summary: LogDelta - Go Beyond Grepping with NLP-based Log File Analysis
Author-email: Mika Mäntylä <mika.mantyla@helsinki.fi>
Keywords: logs,anomaly detection,log parsing
Classifier: Development Status :: 4 - Beta
Classifier: Intended Audience :: Education
Classifier: Intended Audience :: Science/Research
Classifier: Intended Audience :: Information Technology
Classifier: License :: OSI Approved :: MIT License
Classifier: Programming Language :: Python :: 3
Classifier: Programming Language :: Python :: 3.9
Classifier: Programming Language :: Python :: 3.10
Classifier: Programming Language :: Python :: 3.11
Classifier: Programming Language :: Python :: 3.12
Classifier: Topic :: Scientific/Engineering :: Mathematics
Classifier: Topic :: Software Development :: Libraries :: Python Modules
Classifier: Topic :: System :: Logging
Requires-Python: <3.13,>=3.9
Requires-Dist: loglead>=1.2.1
Requires-Dist: XlsxWriter
